[
  {
    "id": "ID-1767646423741",
    "name": "Supermarché",
    "owner": "RnJpc2NoaGVyeiBN",
    "status": "En cours",
    "start": "2026-01-05",
    "end": "2026-02-07",
    "progress": 31
  },
  {
    "id": "ID-1767646438549",
    "name": "Création du kitting PRM dans OT",
    "owner": "RGVmaXggQw==",
    "status": "En cours",
    "start": "2026-01-05",
    "end": "2026-01-29",
    "progress": 43
  },
  {
    "id": "ID-1767646460573",
    "name": "Gestions des contenants vides",
    "owner": "QmF0aXN0YSBzYW5jaGVzIEw=",
    "status": "En cours",
    "start": "2026-01-20",
    "end": "2026-01-29",
    "progress": 30
  },
  {
    "id": "ID-1767697333812",
    "name": "Test",
    "owner": "QmFycmF1ZCBM",
    "status": "Bloqué",
    "start": "2026-01-14",
    "end": "2026-02-07",
    "progress": 0
  }
]